CHANGELOG.md
MANIFEST.in
README.md
requirements.txt
setup.py
doc/conf.py
pandasticsearch/__init__.py
pandasticsearch/client.py
pandasticsearch/dataframe.py
pandasticsearch/errors.py
pandasticsearch/queries.py
pandasticsearch/types.py
pandasticsearch.egg-info/PKG-INFO
pandasticsearch.egg-info/SOURCES.txt
pandasticsearch.egg-info/dependency_links.txt
pandasticsearch.egg-info/requires.txt
pandasticsearch.egg-info/top_level.txt
pandasticsearch/operators/__init__.py
pandasticsearch/operators/aggregator.py
pandasticsearch/operators/filter.py
pandasticsearch/operators/grouper.py
pandasticsearch/operators/sorter.py
tests/__init__.py
tests/test_cilent.py
tests/test_dataframe.py
tests/test_operators.py
tests/test_queries.py
tests/test_types.py