Metadata-Version: 2.1
Name: pandasticsearch
Version: 0.5.4
Summary: A Pandastic Elasticsearch client for data analyzing.
Home-page: http://pypi.python.org/pypi/pandasticsearch/
Author: onesuper
Author-email: onesuperclark@gmail.com
License: MIT
Platform: UNKNOWN
Provides-Extra: pandas
